{"responses":[{"logoAnnotations":[{"mid":"/m/02y1vz","description":"Facebook","score":0.32022977,"boundingPoly":{"vertices":[{"x":1895,"y":1218},{"x":2570,"y":1218},{"x":2570,"y":1373},{"x":1895,"y":1373}]}}],"labelAnnotations":[{"mid":"/m/011s0","description":"advertising","score":0.86979336,"topicality":0.86979336},{"mid":"/m/029zz6","description":"displaydevice","score":0.84815854,"topicality":0.84815854},{"mid":"/m/02_784","description":"displayadvertising","score":0.7638097,"topicality":0.7638097},{"mid":"/m/07c1v","description":"technology","score":0.75452745,"topicality":0.75452745},{"mid":"/m/0bkqqh","description":"signage","score":0.6356947,"topicality":0.6356947},{"mid":"/m/0m9cj","description":"banner","score":0.57381344,"topicality":0.57381344},{"mid":"/m/04gvls_","description":"leddisplay","score":0.56958526,"topicality":0.56958526},{"mid":"/m/06ycgh","description":"projectionscreen","score":0.51617795,"topicality":0.51617795},{"mid":"/m/03gq5hm","description":"font","score":0.5100037,"topicality":0.5100037}],"textAnnotations":[{"locale":"en","description":"facebook\non\nthon\nWifi-Facebook\nPassword-mOvefast\nConnecting\ntheworld\ntakesevery\noneofus\n","boundingPoly":{"vertices":[{"x":842,"y":1141},{"x":3132,"y":1141},{"x":3132,"y":2125},{"x":842,"y":2125}]}},{"description":"facebook","boundingPoly":{"vertices":[{"x":1453,"y":1141},{"x":2588,"y":1141},{"x":2588,"y":1365},{"x":1453,"y":1365}]}},{"description":"on","boundingPoly":{"vertices":[{"x":1666,"y":1464},{"x":1855,"y":1447},{"x":1865,"y":1556},{"x":1675,"y":1573}]}},{"description":"thon","boundingPoly":{"vertices":[{"x":2406,"y":1414},{"x":2778,"y":1426},{"x":2773,"y":1564},{"x":2401,"y":1552}]}},{"description":"Wifi","boundingPoly":{"vertices":[{"x":842,"y":1823},{"x":1095,"y":1823},{"x":1095,"y":1941},{"x":842,"y":1941}]}},{"description":"-","boundingPoly":{"vertices":[{"x":1141,"y":1887},{"x":1204,"y":1887},{"x":1204,"y":1904},{"x":1141,"y":1904}]}},{"description":"Facebook","boundingPoly":{"vertices":[{"x":1251,"y":1817},{"x":1876,"y":1817},{"x":1876,"y":1937},{"x":1251,"y":1937}]}},{"description":"Password","boundingPoly":{"vertices":[{"x":842,"y":2007},{"x":1464,"y":2002},{"x":1465,"y":2119},{"x":843,"y":2124}]}},{"description":"-","boundingPoly":{"vertices":[{"x":1513,"y":2063},{"x":1579,"y":2062},{"x":1579,"y":2123},{"x":1513,"y":2124}]}},{"description":"mOvefast","boundingPoly":{"vertices":[{"x":1596,"y":2001},{"x":2313,"y":1995},{"x":2314,"y":2108},{"x":1597,"y":2114}]}},{"description":"Connecting","boundingPoly":{"vertices":[{"x":2976,"y":1910},{"x":3131,"y":1909},{"x":3131,"y":1929},{"x":2976,"y":1930}]}},{"description":"the","boundingPoly":{"vertices":[{"x":2976,"y":1941},{"x":3017,"y":1941},{"x":3017,"y":1961},{"x":2976,"y":1961}]}},{"description":"world","boundingPoly":{"vertices":[{"x":3024,"y":1939},{"x":3100,"y":1939},{"x":3100,"y":1961},{"x":3024,"y":1961}]}},{"description":"takes","boundingPoly":{"vertices":[{"x":2976,"y":1968},{"x":3046,"y":1968},{"x":3046,"y":1990},{"x":2976,"y":1990}]}},{"description":"every","boundingPoly":{"vertices":[{"x":3055,"y":1974},{"x":3129,"y":1974},{"x":3129,"y":1996},{"x":3055,"y":1996}]}},{"description":"one","boundingPoly":{"vertices":[{"x":2977,"y":2005},{"x":3022,"y":2004},{"x":3022,"y":2018},{"x":2977,"y":2019}]}},{"description":"of","boundingPoly":{"vertices":[{"x":3032,"y":1999},{"x":3056,"y":1999},{"x":3056,"y":2019},{"x":3032,"y":2019}]}},{"description":"us","boundingPoly":{"vertices":[{"x":3065,"y":2003},{"x":3095,"y":2003},{"x":3095,"y":2017},{"x":3065,"y":2017}]}}],"fullTextAnnotation":{"pages":[{"property":{"detectedLanguages":[{"languageCode":"en"}]},"width":3968,"height":2976,"blocks":[{"property":{"detectedLanguages":[{"languageCode":"en"}]},"boundingBox":{"vertices":[{"x":1453,"y":1141},{"x":2588,"y":1141},{"x":2588,"y":1365},{"x":1453,"y":1365}]},"paragraphs":[{"property":{"detectedLanguages":[{"languageCode":"en"}]},"boundingBox":{"vertices":[{"x":1453,"y":1141},{"x":2588,"y":1141},{"x":2588,"y":1365},{"x":1453,"y":1365}]},"words":[{"property":{"detectedLanguages":[{"languageCode":"en"}]},"boundingBox":{"vertices":[{"x":1453,"y":1141},{"x":2588,"y":1141},{"x":2588,"y":1365},{"x":1453,"y":1365}]},"symbols":[{"property":{"detectedLanguages":[{"languageCode":"en"}]},"boundingBox":{"vertices":[{"x":1453,"y":1141},{"x":1569,"y":1141},{"x":1569,"y":1361},{"x":1453,"y":1361}]},"text":"f"},{"property":{"detectedLanguages":[{"languageCode":"en"}]},"boundingBox":{"vertices":[{"x":1565,"y":1210},{"x":1704,"y":1210},{"x":1704,"y":1365},{"x":1565,"y":1365}]},"text":"a"},{"property":{"detectedLanguages":[{"languageCode":"en"}]},"boundingBox":{"vertices":[{"x":1705,"y":1210},{"x":1840,"y":1210},{"x":1840,"y":1365},{"x":1705,"y":1365}]},"text":"c"},{"property":{"detectedLanguages":[{"languageCode":"en"}]},"boundingBox":{"vertices":[{"x":1836,"y":1210},{"x":1975,"y":1210},{"x":1975,"y":1365},{"x":1836,"y":1365}]},"text":"e"},{"property":{"detectedLanguages":[{"languageCode":"en"}]},"boundingBox":{"vertices":[{"x":1984,"y":1141},{"x":2135,"y":1141},{"x":2135,"y":1361},{"x":1984,"y":1361}]},"text":"b"},{"property":{"detectedLanguages":[{"languageCode":"en"}]},"boundingBox":{"vertices":[{"x":2139,"y":1207},{"x":2286,"y":1207},{"x":2286,"y":1362},{"x":2139,"y":1362}]},"text":"o"},{"property":{"detectedLanguages":[{"languageCode":"en"}]},"boundingBox":{"vertices":[{"x":2294,"y":1207},{"x":2445,"y":1207},{"x":2445,"y":1358},{"x":2294,"y":1358}]},"text":"o"},{"property":{"detectedLanguages":[{"languageCode":"en"}],"detectedBreak":{"type":"EOL_SURE_SPACE"}},"boundingBox":{"vertices":[{"x":2449,"y":1141},{"x":2588,"y":1141},{"x":2588,"y":1358},{"x":2449,"y":1358}]},"text":"k"}]}]}],"blockType":"TEXT"},{"property":{"detectedLanguages":[{"languageCode":"en"}]},"boundingBox":{"vertices":[{"x":1666,"y":1447},{"x":1867,"y":1447},{"x":1867,"y":1574},{"x":1666,"y":1574}]},"paragraphs":[{"property":{"detectedLanguages":[{"languageCode":"en"}]},"boundingBox":{"vertices":[{"x":1666,"y":1447},{"x":1867,"y":1447},{"x":1867,"y":1574},{"x":1666,"y":1574}]},"words":[{"property":{"detectedLanguages":[{"languageCode":"en"}]},"boundingBox":{"vertices":[{"x":1666,"y":1464},{"x":1855,"y":1447},{"x":1865,"y":1556},{"x":1675,"y":1573}]},"symbols":[{"property":{"detectedLanguages":[{"languageCode":"en"}]},"boundingBox":{"vertices":[{"x":1666,"y":1464},{"x":1758,"y":1456},{"x":1766,"y":1555},{"x":1675,"y":1563}]},"text":"o"},{"property":{"detectedLanguages":[{"languageCode":"en"}],"detectedBreak":{"type":"EOL_SURE_SPACE"}},"boundingBox":{"vertices":[{"x":1767,"y":1462},{"x":1857,"y":1454},{"x":1865,"y":1555},{"x":1776,"y":1563}]},"text":"n"}]}]}],"blockType":"TEXT"},{"property":{"detectedLanguages":[{"languageCode":"tt"}]},"boundingBox":{"vertices":[{"x":2402,"y":1414},{"x":2779,"y":1414},{"x":2779,"y":1565},{"x":2402,"y":1565}]},"paragraphs":[{"property":{"detectedLanguages":[{"languageCode":"tt"}]},"boundingBox":{"vertices":[{"x":2402,"y":1414},{"x":2779,"y":1414},{"x":2779,"y":1565},{"x":2402,"y":1565}]},"words":[{"property":{"detectedLanguages":[{"languageCode":"tt"}]},"boundingBox":{"vertices":[{"x":2406,"y":1414},{"x":2778,"y":1426},{"x":2773,"y":1564},{"x":2401,"y":1552}]},"symbols":[{"property":{"detectedLanguages":[{"languageCode":"en"}]},"boundingBox":{"vertices":[{"x":2406,"y":1433},{"x":2468,"y":1435},{"x":2464,"y":1554},{"x":2402,"y":1552}]},"text":"t"},{"property":{"detectedLanguages":[{"languageCode":"en"}]},"boundingBox":{"vertices":[{"x":2474,"y":1416},{"x":2566,"y":1419},{"x":2561,"y":1557},{"x":2469,"y":1554}]},"text":"h"},{"property":{"detectedLanguages":[{"languageCode":"en"}]},"boundingBox":{"vertices":[{"x":2576,"y":1451},{"x":2675,"y":1454},{"x":2672,"y":1553},{"x":2573,"y":1550}]},"text":"o"},{"property":{"detectedLanguages":[{"languageCode":"en"}],"detectedBreak":{"type":"EOL_SURE_SPACE"}},"boundingBox":{"vertices":[{"x":2677,"y":1455},{"x":2776,"y":1458},{"x":2773,"y":1557},{"x":2674,"y":1554}]},"text":"n"}]}]}],"blockType":"TEXT"},{"property":{"detectedLanguages":[{"languageCode":"en"}]},"boundingBox":{"vertices":[{"x":842,"y":1817},{"x":2314,"y":1817},{"x":2314,"y":2125},{"x":842,"y":2125}]},"paragraphs":[{"property":{"detectedLanguages":[{"languageCode":"en"}]},"boundingBox":{"vertices":[{"x":842,"y":1817},{"x":2314,"y":1817},{"x":2314,"y":2125},{"x":842,"y":2125}]},"words":[{"property":{"detectedLanguages":[{"languageCode":"en"}]},"boundingBox":{"vertices":[{"x":842,"y":1823},{"x":1095,"y":1823},{"x":1095,"y":1941},{"x":842,"y":1941}]},"symbols":[{"property":{"detectedLanguages":[{"languageCode":"en"}]},"boundingBox":{"vertices":[{"x":842,"y":1832},{"x":919,"y":1832},{"x":919,"y":1940},{"x":842,"y":1940}]},"text":"W"},{"property":{"detectedLanguages":[{"languageCode":"en"}]},"boundingBox":{"vertices":[{"x":920,"y":1832},{"x":1001,"y":1832},{"x":1001,"y":1940},{"x":920,"y":1940}]},"text":"i"},{"property":{"detectedLanguages":[{"languageCode":"en"}]},"boundingBox":{"vertices":[{"x":1015,"y":1823},{"x":1053,"y":1823},{"x":1053,"y":1941},{"x":1015,"y":1941}]},"text":"f"},{"property":{"detectedLanguages":[{"languageCode":"en"}],"detectedBreak":{"type":"SPACE"}},"boundingBox":{"vertices":[{"x":1054,"y":1823},{"x":1096,"y":1823},{"x":1096,"y":1941},{"x":1054,"y":1941}]},"text":"i"}]},{"property":{"detectedLanguages":[{"languageCode":"en"}]},"boundingBox":{"vertices":[{"x":1141,"y":1887},{"x":1204,"y":1887},{"x":1204,"y":1904},{"x":1141,"y":1904}]},"symbols":[{"property":{"detectedLanguages":[{"languageCode":"en"}],"detectedBreak":{"type":"SPACE"}},"boundingBox":{"vertices":[{"x":1141,"y":1887},{"x":1204,"y":1887},{"x":1204,"y":1904},{"x":1141,"y":1904}]},"text":"-"}]},{"property":{"detectedLanguages":[{"languageCode":"en"}]},"boundingBox":{"vertices":[{"x":1251,"y":1817},{"x":1876,"y":1817},{"x":1876,"y":1937},{"x":1251,"y":1937}]},"symbols":[{"property":{"detectedLanguages":[{"languageCode":"en"}]},"boundingBox":{"vertices":[{"x":1251,"y":1832},{"x":1314,"y":1832},{"x":1314,"y":1936},{"x":1251,"y":1936}]},"text":"F"},{"property":{"detectedLanguages":[{"languageCode":"en"}]},"boundingBox":{"vertices":[{"x":1325,"y":1852},{"x":1394,"y":1852},{"x":1394,"y":1937},{"x":1325,"y":1937}]},"text":"a"},{"property":{"detectedLanguages":[{"languageCode":"en"}]},"boundingBox":{"vertices":[{"x":1395,"y":1852},{"x":1464,"y":1852},{"x":1464,"y":1937},{"x":1395,"y":1937}]},"text":"c"},{"property":{"detectedLanguages":[{"languageCode":"en"}]},"boundingBox":{"vertices":[{"x":1474,"y":1852},{"x":1541,"y":1852},{"x":1541,"y":1935},{"x":1474,"y":1935}]},"text":"e"},{"property":{"detectedLanguages":[{"languageCode":"en"}]},"boundingBox":{"vertices":[{"x":1557,"y":1821},{"x":1636,"y":1821},{"x":1636,"y":1935},{"x":1557,"y":1935}]},"text":"b"},{"property":{"detectedLanguages":[{"languageCode":"en"}]},"boundingBox":{"vertices":[{"x":1637,"y":1821},{"x":1712,"y":1821},{"x":1712,"y":1935},{"x":1637,"y":1935}]},"text":"o"},{"property":{"detectedLanguages":[{"languageCode":"en"}]},"boundingBox":{"vertices":[{"x":1722,"y":1817},{"x":1801,"y":1817},{"x":1801,"y":1931},{"x":1722,"y":1931}]},"text":"o"},{"property":{"detectedLanguages":[{"languageCode":"en"}],"detectedBreak":{"type":"EOL_SURE_SPACE"}},"boundingBox":{"vertices":[{"x":1801,"y":1817},{"x":1876,"y":1817},{"x":1876,"y":1931},{"x":1801,"y":1931}]},"text":"k"}]},{"property":{"detectedLanguages":[{"languageCode":"en"}]},"boundingBox":{"vertices":[{"x":842,"y":2007},{"x":1464,"y":2002},{"x":1465,"y":2119},{"x":843,"y":2124}]},"symbols":[{"property":{"detectedLanguages":[{"languageCode":"en"}]},"boundingBox":{"vertices":[{"x":842,"y":2016},{"x":906,"y":2015},{"x":907,"y":2118},{"x":843,"y":2119}]},"text":"P"},{"property":{"detectedLanguages":[{"languageCode":"en"}]},"boundingBox":{"vertices":[{"x":918,"y":2036},{"x":988,"y":2035},{"x":989,"y":2123},{"x":919,"y":2124}]},"text":"a"},{"property":{"detectedLanguages":[{"languageCode":"en"}]},"boundingBox":{"vertices":[{"x":990,"y":2034},{"x":1056,"y":2033},{"x":1057,"y":2121},{"x":991,"y":2122}]},"text":"s"},{"property":{"detectedLanguages":[{"languageCode":"en"}]},"boundingBox":{"vertices":[{"x":1069,"y":2038},{"x":1155,"y":2037},{"x":1156,"y":2117},{"x":1070,"y":2118}]},"text":"s"},{"property":{"detectedLanguages":[{"languageCode":"en"}]},"boundingBox":{"vertices":[{"x":1156,"y":2038},{"x":1240,"y":2037},{"x":1241,"y":2117},{"x":1157,"y":2118}]},"text":"w"},{"property":{"detectedLanguages":[{"languageCode":"en"}]},"boundingBox":{"vertices":[{"x":1253,"y":2032},{"x":1319,"y":2031},{"x":1320,"y":2115},{"x":1254,"y":2116}]},"text":"o"},{"property":{"detectedLanguages":[{"languageCode":"en"}]},"boundingBox":{"vertices":[{"x":1321,"y":2032},{"x":1387,"y":2031},{"x":1388,"y":2115},{"x":1322,"y":2116}]},"text":"r"},{"property":{"detectedLanguages":[{"languageCode":"en"}],"detectedBreak":{"type":"SPACE"}},"boundingBox":{"vertices":[{"x":1395,"y":2003},{"x":1465,"y":2002},{"x":1466,"y":2115},{"x":1396,"y":2116}]},"text":"d"}]},{"property":{"detectedLanguages":[{"languageCode":"en"}]},"boundingBox":{"vertices":[{"x":1513,"y":2063},{"x":1579,"y":2062},{"x":1579,"y":2123},{"x":1513,"y":2124}]},"symbols":[{"property":{"detectedLanguages":[{"languageCode":"en"}],"detectedBreak":{"type":"SPACE"}},"boundingBox":{"vertices":[{"x":1513,"y":2063},{"x":1579,"y":2062},{"x":1579,"y":2123},{"x":1513,"y":2124}]},"text":"-"}]},{"property":{"detectedLanguages":[{"languageCode":"sk"}]},"boundingBox":{"vertices":[{"x":1596,"y":2001},{"x":2313,"y":1995},{"x":2314,"y":2108},{"x":1597,"y":2114}]},"symbols":[{"property":{"detectedLanguages":[{"languageCode":"en"}]},"boundingBox":{"vertices":[{"x":1596,"y":2034},{"x":1695,"y":2033},{"x":1696,"y":2111},{"x":1597,"y":2112}]},"text":"m"},{"property":{"detectedLanguages":[{"languageCode":"en"}]},"boundingBox":{"vertices":[{"x":1710,"y":2003},{"x":1788,"y":2002},{"x":1789,"y":2109},{"x":1711,"y":2110}]},"text":"O"},{"property":{"detectedLanguages":[{"languageCode":"en"}]},"boundingBox":{"vertices":[{"x":1790,"y":2003},{"x":1868,"y":2002},{"x":1869,"y":2109},{"x":1791,"y":2110}]},"text":"v"},{"property":{"detectedLanguages":[{"languageCode":"en"}]},"boundingBox":{"vertices":[{"x":1891,"y":2028},{"x":1957,"y":2027},{"x":1958,"y":2111},{"x":1892,"y":2112}]},"text":"e"},{"property":{"detectedLanguages":[{"languageCode":"en"}]},"boundingBox":{"vertices":[{"x":1982,"y":1997},{"x":2046,"y":1996},{"x":2047,"y":2107},{"x":1983,"y":2108}]},"text":"f"},{"property":{"detectedLanguages":[{"languageCode":"en"}]},"boundingBox":{"vertices":[{"x":2071,"y":2026},{"x":2145,"y":2025},{"x":2146,"y":2109},{"x":2072,"y":2110}]},"text":"a"},{"property":{"detectedLanguages":[{"languageCode":"en"}]},"boundingBox":{"vertices":[{"x":2146,"y":2026},{"x":2222,"y":2025},{"x":2223,"y":2109},{"x":2147,"y":2110}]},"text":"s"},{"property":{"detectedLanguages":[{"languageCode":"en"}],"detectedBreak":{"type":"EOL_SURE_SPACE"}},"boundingBox":{"vertices":[{"x":2251,"y":2005},{"x":2313,"y":2005},{"x":2314,"y":2108},{"x":2252,"y":2108}]},"text":"t"}]}]}],"blockType":"TEXT"},{"property":{"detectedLanguages":[{"languageCode":"en"}]},"boundingBox":{"vertices":[{"x":2976,"y":1910},{"x":3132,"y":1910},{"x":3132,"y":2020},{"x":2976,"y":2020}]},"paragraphs":[{"property":{"detectedLanguages":[{"languageCode":"en"}]},"boundingBox":{"vertices":[{"x":2976,"y":1910},{"x":3132,"y":1910},{"x":3132,"y":2020},{"x":2976,"y":2020}]},"words":[{"property":{"detectedLanguages":[{"languageCode":"en"}]},"boundingBox":{"vertices":[{"x":2976,"y":1910},{"x":3131,"y":1909},{"x":3131,"y":1929},{"x":2976,"y":1930}]},"symbols":[{"property":{"detectedLanguages":[{"languageCode":"en"}]},"boundingBox":{"vertices":[{"x":2976,"y":1910},{"x":2992,"y":1910},{"x":2992,"y":1930},{"x":2976,"y":1930}]},"text":"C"},{"property":{"detectedLanguages":[{"languageCode":"en"}]},"boundingBox":{"vertices":[{"x":2993,"y":1916},{"x":3009,"y":1916},{"x":3009,"y":1930},{"x":2993,"y":1930}]},"text":"o"},{"property":{"detectedLanguages":[{"languageCode":"en"}]},"boundingBox":{"vertices":[{"x":3010,"y":1916},{"x":3024,"y":1916},{"x":3024,"y":1930},{"x":3010,"y":1930}]},"text":"n"},{"property":{"detectedLanguages":[{"languageCode":"en"}]},"boundingBox":{"vertices":[{"x":3028,"y":1916},{"x":3044,"y":1916},{"x":3044,"y":1930},{"x":3028,"y":1930}]},"text":"n"},{"property":{"detectedLanguages":[{"languageCode":"en"}]},"boundingBox":{"vertices":[{"x":3045,"y":1916},{"x":3059,"y":1916},{"x":3059,"y":1930},{"x":3045,"y":1930}]},"text":"e"},{"property":{"detectedLanguages":[{"languageCode":"en"}]},"boundingBox":{"vertices":[{"x":3063,"y":1914},{"x":3073,"y":1914},{"x":3073,"y":1930},{"x":3063,"y":1930}]},"text":"c"},{"property":{"detectedLanguages":[{"languageCode":"en"}]},"boundingBox":{"vertices":[{"x":3074,"y":1914},{"x":3082,"y":1914},{"x":3082,"y":1930},{"x":3074,"y":1930}]},"text":"t"},{"property":{"detectedLanguages":[{"languageCode":"en"}]},"boundingBox":{"vertices":[{"x":3084,"y":1914},{"x":3094,"y":1914},{"x":3094,"y":1930},{"x":3084,"y":1930}]},"text":"i"},{"property":{"detectedLanguages":[{"languageCode":"en"}]},"boundingBox":{"vertices":[{"x":3098,"y":1916},{"x":3114,"y":1916},{"x":3114,"y":1930},{"x":3098,"y":1930}]},"text":"n"},{"property":{"detectedLanguages":[{"languageCode":"en"}],"detectedBreak":{"type":"EOL_SURE_SPACE"}},"boundingBox":{"vertices":[{"x":3115,"y":1916},{"x":3131,"y":1916},{"x":3131,"y":1930},{"x":3115,"y":1930}]},"text":"g"}]},{"property":{"detectedLanguages":[{"languageCode":"en"}]},"boundingBox":{"vertices":[{"x":2976,"y":1941},{"x":3017,"y":1941},{"x":3017,"y":1961},{"x":2976,"y":1961}]},"symbols":[{"property":{"detectedLanguages":[{"languageCode":"en"}]},"boundingBox":{"vertices":[{"x":2976,"y":1941},{"x":2986,"y":1941},{"x":2986,"y":1961},{"x":2976,"y":1961}]},"text":"t"},{"property":{"detectedLanguages":[{"languageCode":"en"}]},"boundingBox":{"vertices":[{"x":2987,"y":1941},{"x":3001,"y":1941},{"x":3001,"y":1961},{"x":2987,"y":1961}]},"text":"h"},{"property":{"detectedLanguages":[{"languageCode":"en"}],"detectedBreak":{"type":"SPACE"}},"boundingBox":{"vertices":[{"x":3003,"y":1947},{"x":3017,"y":1947},{"x":3017,"y":1961},{"x":3003,"y":1961}]},"text":"e"}]},{"property":{"detectedLanguages":[{"languageCode":"en"}]},"boundingBox":{"vertices":[{"x":3024,"y":1939},{"x":3100,"y":1939},{"x":3100,"y":1961},{"x":3024,"y":1961}]},"symbols":[{"property":{"detectedLanguages":[{"languageCode":"en"}]},"boundingBox":{"vertices":[{"x":3024,"y":1947},{"x":3048,"y":1947},{"x":3048,"y":1961},{"x":3024,"y":1961}]},"text":"w"},{"property":{"detectedLanguages":[{"languageCode":"en"}]},"boundingBox":{"vertices":[{"x":3049,"y":1947},{"x":3063,"y":1947},{"x":3063,"y":1961},{"x":3049,"y":1961}]},"text":"o"},{"property":{"detectedLanguages":[{"languageCode":"en"}]},"boundingBox":{"vertices":[{"x":3065,"y":1939},{"x":3073,"y":1939},{"x":3073,"y":1961},{"x":3065,"y":1961}]},"text":"r"},{"property":{"detectedLanguages":[{"languageCode":"en"}]},"boundingBox":{"vertices":[{"x":3074,"y":1939},{"x":3080,"y":1939},{"x":3080,"y":1961},{"x":3074,"y":1961}]},"text":"l"},{"property":{"detectedLanguages":[{"languageCode":"en"}],"detectedBreak":{"type":"EOL_SURE_SPACE"}},"boundingBox":{"vertices":[{"x":3084,"y":1939},{"x":3100,"y":1939},{"x":3100,"y":1961},{"x":3084,"y":1961}]},"text":"d"}]},{"property":{"detectedLanguages":[{"languageCode":"en"}]},"boundingBox":{"vertices":[{"x":2976,"y":1968},{"x":3046,"y":1968},{"x":3046,"y":1990},{"x":2976,"y":1990}]},"symbols":[{"property":{"detectedLanguages":[{"languageCode":"en"}]},"boundingBox":{"vertices":[{"x":2976,"y":1970},{"x":2982,"y":1970},{"x":2982,"y":1988},{"x":2976,"y":1988}]},"text":"t"},{"property":{"detectedLanguages":[{"languageCode":"en"}]},"boundingBox":{"vertices":[{"x":2985,"y":1974},{"x":2999,"y":1974},{"x":2999,"y":1988},{"x":2985,"y":1988}]},"text":"a"},{"property":{"detectedLanguages":[{"languageCode":"en"}]},"boundingBox":{"vertices":[{"x":3003,"y":1968},{"x":3017,"y":1968},{"x":3017,"y":1990},{"x":3003,"y":1990}]},"text":"k"},{"property":{"detectedLanguages":[{"languageCode":"en"}]},"boundingBox":{"vertices":[{"x":3018,"y":1974},{"x":3032,"y":1974},{"x":3032,"y":1990},{"x":3018,"y":1990}]},"text":"e"},{"property":{"detectedLanguages":[{"languageCode":"en"}],"detectedBreak":{"type":"SPACE"}},"boundingBox":{"vertices":[{"x":3034,"y":1974},{"x":3046,"y":1974},{"x":3046,"y":1990},{"x":3034,"y":1990}]},"text":"s"}]},{"property":{"detectedLanguages":[{"languageCode":"en"}]},"boundingBox":{"vertices":[{"x":3055,"y":1974},{"x":3129,"y":1974},{"x":3129,"y":1996},{"x":3055,"y":1996}]},"symbols":[{"property":{"detectedLanguages":[{"languageCode":"en"}]},"boundingBox":{"vertices":[{"x":3055,"y":1974},{"x":3067,"y":1974},{"x":3067,"y":1990},{"x":3055,"y":1990}]},"text":"e"},{"property":{"detectedLanguages":[{"languageCode":"en"}]},"boundingBox":{"vertices":[{"x":3070,"y":1974},{"x":3084,"y":1974},{"x":3084,"y":1988},{"x":3070,"y":1988}]},"text":"v"},{"property":{"detectedLanguages":[{"languageCode":"en"}]},"boundingBox":{"vertices":[{"x":3086,"y":1974},{"x":3100,"y":1974},{"x":3100,"y":1988},{"x":3086,"y":1988}]},"text":"e"},{"property":{"detectedLanguages":[{"languageCode":"en"}]},"boundingBox":{"vertices":[{"x":3101,"y":1974},{"x":3109,"y":1974},{"x":3109,"y":1988},{"x":3101,"y":1988}]},"text":"r"},{"property":{"detectedLanguages":[{"languageCode":"en"}],"detectedBreak":{"type":"EOL_SURE_SPACE"}},"boundingBox":{"vertices":[{"x":3115,"y":1974},{"x":3129,"y":1974},{"x":3129,"y":1996},{"x":3115,"y":1996}]},"text":"y"}]},{"property":{"detectedLanguages":[{"languageCode":"en"}]},"boundingBox":{"vertices":[{"x":2977,"y":2005},{"x":3022,"y":2004},{"x":3022,"y":2018},{"x":2977,"y":2019}]},"symbols":[{"property":{"detectedLanguages":[{"languageCode":"en"}]},"boundingBox":{"vertices":[{"x":2977,"y":2005},{"x":2991,"y":2005},{"x":2991,"y":2019},{"x":2977,"y":2019}]},"text":"o"},{"property":{"detectedLanguages":[{"languageCode":"en"}]},"boundingBox":{"vertices":[{"x":2993,"y":2005},{"x":3007,"y":2005},{"x":3007,"y":2019},{"x":2993,"y":2019}]},"text":"n"},{"property":{"detectedLanguages":[{"languageCode":"en"}],"detectedBreak":{"type":"SPACE"}},"boundingBox":{"vertices":[{"x":3010,"y":2005},{"x":3022,"y":2005},{"x":3022,"y":2019},{"x":3010,"y":2019}]},"text":"e"}]},{"property":{"detectedLanguages":[{"languageCode":"en"}]},"boundingBox":{"vertices":[{"x":3032,"y":1999},{"x":3056,"y":1999},{"x":3056,"y":2019},{"x":3032,"y":2019}]},"symbols":[{"property":{"detectedLanguages":[{"languageCode":"en"}]},"boundingBox":{"vertices":[{"x":3032,"y":1999},{"x":3042,"y":1999},{"x":3042,"y":2019},{"x":3032,"y":2019}]},"text":"o"},{"property":{"detectedLanguages":[{"languageCode":"en"}],"detectedBreak":{"type":"SPACE"}},"boundingBox":{"vertices":[{"x":3043,"y":1999},{"x":3055,"y":1999},{"x":3055,"y":2019},{"x":3043,"y":2019}]},"text":"f"}]},{"property":{"detectedLanguages":[{"languageCode":"en"}]},"boundingBox":{"vertices":[{"x":3065,"y":2003},{"x":3095,"y":2003},{"x":3095,"y":2017},{"x":3065,"y":2017}]},"symbols":[{"property":{"detectedLanguages":[{"languageCode":"en"}]},"boundingBox":{"vertices":[{"x":3065,"y":2003},{"x":3079,"y":2003},{"x":3079,"y":2017},{"x":3065,"y":2017}]},"text":"u"},{"property":{"detectedLanguages":[{"languageCode":"en"}],"detectedBreak":{"type":"EOL_SURE_SPACE"}},"boundingBox":{"vertices":[{"x":3082,"y":2003},{"x":3094,"y":2003},{"x":3094,"y":2017},{"x":3082,"y":2017}]},"text":"s"}]}]}],"blockType":"TEXT"}]}],"text":"facebook\non\nthon\nWifi-Facebook\nPassword-mOvefast\nConnecting\ntheworld\ntakesevery\noneofus\n"}}]}